frogbox/__init__.py
frogbox/cli.py
frogbox/config.py
frogbox/utils.py
frogbox/callbacks/__init__.py
frogbox/callbacks/callback.py
frogbox/callbacks/image_logger.py
frogbox/data/__init__.py
frogbox/data/dataset.py
frogbox/data/model.py
frogbox/data/train_supervised.py
frogbox/engines/__init__.py
frogbox/engines/engine.py
frogbox/engines/events.py
frogbox/engines/gan.py
frogbox/engines/supervised.py
frogbox/handlers/__init__.py
frogbox/handlers/checkpoint.py
frogbox/handlers/composite_loss_logger.py
frogbox/handlers/metric_logger.py
frogbox/handlers/optimizer_logger.py
frogbox/handlers/output_logger.py
frogbox/metrics/__init__.py
frogbox/pipelines/__init__.py
frogbox/pipelines/composite_loss.py
frogbox/pipelines/gan.py
frogbox/pipelines/lr_scheduler.py
frogbox/pipelines/name_generation.py
frogbox/pipelines/pipeline.py
frogbox/pipelines/supervised.py
frogbox-0.5.3.dist-info/licenses/LICENSE
frogbox-0.5.3.dist-info/METADATA
frogbox-0.5.3.dist-info/WHEEL
frogbox-0.5.3.dist-info/entry_points.txt
frogbox-0.5.3.dist-info/top_level.txt
frogbox-0.5.3.dist-info/RECORD
