Metadata-Version: 2.4
Name: frogbox
Version: 0.5.3
Summary: An opinionated machine learning framework
Author-email: "Simon J. Larsen" <simonhffh@gmail.com>
License-Expression: MIT
Project-URL: Homepage, https://hisimon.dk/frogbox
Project-URL: Issues, https://github.com/SimonLarsen/frogbox/issues
Requires-Python: >=3.10
License-File: LICENSE
Requires-Dist: torch>=2.5.1
Requires-Dist: torchvision>=0.20.1
Requires-Dist: accelerate>=1.2.0
Requires-Dist: torchmetrics>=1.6.0
Requires-Dist: pydantic>=2.10.3
Requires-Dist: tqdm>=4.67.1
Requires-Dist: wandb>=0.18.7
Requires-Dist: jinja2>=3.1.4
Requires-Dist: click>=8.1.7
Dynamic: license-file
